HISTORY.rst
LICENSE
MANIFEST.in
README.rst
setup.py
getme/__init__.py
getme/models.py
getme.egg-info/PKG-INFO
getme.egg-info/SOURCES.txt
getme.egg-info/dependency_links.txt
getme.egg-info/not-zip-safe
getme.egg-info/requires.txt
getme.egg-info/top_level.txt