Metadata-Version: 1.1
Name: getme
Version: 0.0.1
Summary: AN HTML extractor by a simple template
Home-page: UNKNOWN
Author: Quang Quach
Author-email: me@quang.be
License: Copyright (c) 2013 by Quang Quach and contributors. See AUTHORS
